pywebexec/__init__.py
pywebexec/host_ip.py
pywebexec/pywebexec.py
pywebexec/swagger.yaml
pywebexec/version.py
pywebexec/static/css/form.css
pywebexec/static/css/markdown.css
pywebexec/static/css/style.css
pywebexec/static/css/swagger-ui.css
pywebexec/static/css/swagger-ui.css.map
pywebexec/static/css/xterm.css
pywebexec/static/fonts/CommitMonoNerdFontMono-Regular.ttf
pywebexec/static/fonts/LICENSE
pywebexec/static/fonts/glyphicons-halflings-regular.eot
pywebexec/static/fonts/glyphicons-halflings-regular.svg
pywebexec/static/fonts/glyphicons-halflings-regular.ttf
pywebexec/static/fonts/glyphicons-halflings-regular.woff
pywebexec/static/fonts/glyphicons-halflings-regular.woff2
pywebexec/static/images/aborted.svg
pywebexec/static/images/copy.svg
pywebexec/static/images/copy_ok.svg
pywebexec/static/images/down-arrow.svg
pywebexec/static/images/failed.svg
pywebexec/static/images/favicon.svg
pywebexec/static/images/fit-tty.svg
pywebexec/static/images/fit-win.svg
pywebexec/static/images/font-decrease.svg
pywebexec/static/images/font-increase.svg
pywebexec/static/images/norun.svg
pywebexec/static/images/pause.svg
pywebexec/static/images/popup.svg
pywebexec/static/images/resume.svg
pywebexec/static/images/running.svg
pywebexec/static/images/success.svg
pywebexec/static/images/swagger-ui.svg
pywebexec/static/js/exceljs.min.js
pywebexec/static/js/executables.js
pywebexec/static/js/popup.js
pywebexec/static/js/schemaform.js
pywebexec/static/js/script.js
pywebexec/static/js/swagger-form.js
pywebexec/static/js/tablefilter.js
pywebexec/static/js/js-yaml/LICENSE
pywebexec/static/js/js-yaml/js-yaml.min.js
pywebexec/static/js/marked/LICENSE.md
pywebexec/static/js/marked/marked.min.js
pywebexec/static/js/swagger-ui/LICENSE
pywebexec/static/js/swagger-ui/swagger-ui-bundle.js
pywebexec/static/js/swagger-ui/swagger-ui-standalone-preset.js
pywebexec/static/js/xterm/LICENSE
pywebexec/static/js/xterm/addon-canvas.js
pywebexec/static/js/xterm/addon-canvas.js.map
pywebexec-2.4.28.dist-info/licenses/LICENSE
pywebexec-2.4.28.dist-info/METADATA
pywebexec-2.4.28.dist-info/WHEEL
pywebexec-2.4.28.dist-info/entry_points.txt
pywebexec-2.4.28.dist-info/top_level.txt
pywebexec-2.4.28.dist-info/RECORD
