Metadata-Version: 2.4
Name: pywebexec
Version: 2.4.28
Summary: Simple Python HTTP Exec Server
Home-page: https://github.com/joknarf/pywebexec
Author: Franck Jouvanceau
Maintainer: Franck Jouvanceau
License: MIT License
Project-URL: Homepage, https://github.com/joknarf/pywebexec
Project-URL: Documentation, https://github.com/joknarf/pywebexec/blob/main/README.md
Project-URL: Repository, https://github.com/joknarf/pywebexec.git
Keywords: http,server,remote commands,api,website
Classifier: Development Status :: 5 - Production/Stable
Classifier: Intended Audience :: System Administrators
Classifier: License :: OSI Approved :: MIT License
Classifier: Operating System :: POSIX
Classifier: Operating System :: Unix
Classifier: Operating System :: MacOS
Classifier: Programming Language :: Python
Classifier: Programming Language :: Python :: 3
Classifier: Programming Language :: Python :: 3.6
Classifier: Programming Language :: Python :: 3.7
Classifier: Programming Language :: Python :: 3.8
Classifier: Programming Language :: Python :: 3.9
Classifier: Programming Language :: Python :: 3.10
Classifier: Programming Language :: Python :: 3.11
Classifier: Topic :: Software Development :: Libraries :: Python Modules
Classifier: Topic :: System :: Clustering
Classifier: Topic :: System :: Networking
Classifier: Topic :: System :: Systems Administration
Requires-Python: >=3.6
License-File: LICENSE
Requires-Dist: python-daemon>=2.3.2; platform_system != "Windows"
Requires-Dist: cryptography>=40.0.2
Requires-Dist: Flask>=2.0.3
Requires-Dist: Flask-HTTPAuth>=4.8.0
Requires-Dist: pexpect>=4.9.0
Requires-Dist: gunicorn>=21.2.0; platform_system != "Windows"
Requires-Dist: ldap3>=2.9.1
Requires-Dist: pyte>=0.8.1
Requires-Dist: PyYAML>=6.0.1
Requires-Dist: run-para>=1.0.2
Requires-Dist: waitress>=3.0.2; platform_system == "Windows"
Requires-Dist: pywinpty>=2.0.15; platform_system == "Windows"
Dynamic: license-file
